ukb/__init__.py
ukb/__main__.py
ukb/atlas.py
ukb/cli.py
ukb/clip.py
ukb/connectivity.txt
ukb/mesh.py
ukb/surface.py
ukb_atlas-1.0.1.dist-info/licenses/LICENSE
ukb_atlas-1.0.1.dist-info/METADATA
ukb_atlas-1.0.1.dist-info/WHEEL
ukb_atlas-1.0.1.dist-info/entry_points.txt
ukb_atlas-1.0.1.dist-info/top_level.txt
ukb_atlas-1.0.1.dist-info/RECORD
