Metadata-Version: 2.4
Name: ukb_atlas
Version: 1.0.1
Summary: Generate meshes from UK Biobank data
Author-email: Henrik Finsberg <henriknf@simula.no>
License: MIT License
Requires-Python: >=3.10
License-File: LICENSE
Requires-Dist: h5py
Requires-Dist: meshio
Requires-Dist: numpy
Provides-Extra: test
Requires-Dist: pytest; extra == "test"
Requires-Dist: pytest-cov; extra == "test"
Requires-Dist: pyvista; extra == "test"
Requires-Dist: gmsh; extra == "test"
Provides-Extra: dev
Requires-Dist: bump-my-version; extra == "dev"
Requires-Dist: pre-commit; extra == "dev"
Provides-Extra: pyvista
Requires-Dist: pyvista; extra == "pyvista"
Provides-Extra: gmsh
Requires-Dist: gmsh; extra == "gmsh"
Provides-Extra: docs
Requires-Dist: jupyter-book; extra == "docs"
Requires-Dist: jupytext; extra == "docs"
Requires-Dist: jupyter; extra == "docs"
Requires-Dist: pyvista[all]>=0.43.0; extra == "docs"
Requires-Dist: trame-vuetify; extra == "docs"
Requires-Dist: ipywidgets; extra == "docs"
Requires-Dist: gmsh; extra == "docs"
Dynamic: license-file
